{
  "archiveIds": [
    "Swadeshi-Indology-Conference-01",
    "Httpsarchive.orgdetailsSwadeshi-Indology-Conference-02",
    ],
    "useArchiveOrder": true,
    "filePattern": ".*\\.mp3",
    "podcastTemplate": {
      "title": "Swadeshi Indology Conferences",
      "description": "Podcast of all Swadeshi Indology Conferences",
      "imageUrl": "https://archive.org/download/Swadeshi-Indology-Conference-01/artwork-01-hres.jpg",
      "languageCode": "en",
      "publisherEmail": "uttishta.bharata@gmail.com",
      "author": "Rajiv Malhotra",
      "isExplicitYesNo": "no",
      "categories": "Society & Culture"
    }
}
